{"brooke_yufa.md":"03331217","brooke_01.md":"6de040bd","brooke_hhz.md":"f9c56365","demo1_01.md":"24391a0c","brooke2_01.md":"6040c90d","brooke2_02.md":"fc69729c","demo1_index.md":"c6c83f99","demo1_anniu.md":"60ac8bfd","demo1_c.md":"d8ceee6c","demo2_02.md":"1e2d2506","demo2_a.md":"e4bc8d1f","demo2_d.md":"689a3de7","demo1_b.md":"16919949","demo2_01.md":"c0e6e060","demo2_index.md":"d17d3998","demo2_c.md":"ec05379d","demo2_b.md":"fe79fe9d","haohaozhu_xianshang.md":"912d60a3","haohaozhu_01.md":"96e566f4","demo2_index copy.md":"d55555c5","demo1_d.md":"60aeb301","haohaozhu_hhz.md":"b1dad15c","demo1_a.md":"79e84b35","demo1_02.md":"40d00107","index.md":"1aa5b477"}
