{"brooke2_01.md":"e787d59b","demo1_c.md":"6cf4e61b","demo1_d.md":"224b5221","brooke_hhz.md":"6f79b871","brooke2_02.md":"b6802146","demo2_a.md":"f5795fab","demo2_b.md":"05f4ee4d","demo2_c.md":"f6f16847","demo2_d.md":"2c9bd375","demo2_index copy.md":"c6b7a199","demo2_index.md":"de1cf60c","index.md":"e64130ba","demo1_01.md":"a3fc8d01","demo1_02.md":"d7c9d012","demo1_b.md":"cd7fa046","demo2_02.md":"d9e109a2","demo2_01.md":"dc526431","demo1_index.md":"3fbbdeac","demo1_anniu.md":"2eb71d07","demo1_a.md":"60f1c38e"}
